LICENSE
MANIFEST.in
NOTICE
README.md
requirements.txt
setup.cfg
setup.py
Melvan.egg-info/PKG-INFO
Melvan.egg-info/SOURCES.txt
Melvan.egg-info/dependency_links.txt
Melvan.egg-info/not-zip-safe
Melvan.egg-info/requires.txt
Melvan.egg-info/top_level.txt
compiler/__init__.py
compiler/api/__init__.py
compiler/api/compiler.py
compiler/api/source/auth_key.tl
compiler/api/source/main_api.tl
compiler/api/source/sys_msgs.tl
compiler/api/template/combinator.txt
compiler/api/template/type.txt
compiler/errors/__init__.py
compiler/errors/compiler.py
compiler/errors/sort.py
compiler/errors/source/303_SEE_OTHER.tsv
compiler/errors/source/400_BAD_REQUEST.tsv
compiler/errors/source/401_UNAUTHORIZED.tsv
compiler/errors/source/403_FORBIDDEN.tsv
compiler/errors/source/406_NOT_ACCEPTABLE.tsv
compiler/errors/source/420_FLOOD.tsv
compiler/errors/source/500_INTERNAL_SERVER_ERROR.tsv
compiler/errors/source/503_SERVICE_UNAVAILABLE.tsv
compiler/errors/template/class.txt
compiler/errors/template/sub_class.txt
melvan/__init__.py
melvan/client.py
melvan/dispatcher.py
melvan/emoji.py
melvan/file_id.py
melvan/filters.py
melvan/mime_types.py
melvan/py.typed
melvan/sync.py
melvan/utils.py
melvan/connection/__init__.py
melvan/connection/connection.py
melvan/connection/transport/__init__.py
melvan/connection/transport/tcp/__init__.py
melvan/connection/transport/tcp/tcp.py
melvan/connection/transport/tcp/tcp_abridged.py
melvan/connection/transport/tcp/tcp_abridged_o.py
melvan/connection/transport/tcp/tcp_full.py
melvan/connection/transport/tcp/tcp_intermediate.py
melvan/connection/transport/tcp/tcp_intermediate_o.py
melvan/crypto/__init__.py
melvan/crypto/aes.py
melvan/crypto/mtproto.py
melvan/crypto/prime.py
melvan/crypto/rsa.py
melvan/enums/__init__.py
melvan/enums/auto_name.py
melvan/enums/chat_action.py
melvan/enums/chat_event_action.py
melvan/enums/chat_member_status.py
melvan/enums/chat_members_filter.py
melvan/enums/chat_type.py
melvan/enums/message_entity_type.py
melvan/enums/message_media_type.py
melvan/enums/message_service_type.py
melvan/enums/messages_filter.py
melvan/enums/next_code_type.py
melvan/enums/parse_mode.py
melvan/enums/poll_type.py
